lumina_invoice_reader/__init__.py
lumina_invoice_reader/gpt_utils.py
lumina_invoice_reader/image_processing.py
lumina_invoice_reader/invoice_reader.py
lumina_invoice_reader/json_utils.py
lumina_invoice_reader/pdf_processing.py
lumina_invoice_reader-0.0.2.dist-info/METADATA
lumina_invoice_reader-0.0.2.dist-info/WHEEL
lumina_invoice_reader-0.0.2.dist-info/top_level.txt
lumina_invoice_reader-0.0.2.dist-info/RECORD
