Metadata-Version: 2.1
Name: lumina_invoice_reader
Version: 0.0.2
Summary: Convert PDF to structured data
Home-page: https://github.com/CuongTon/lumina_invoice_reader
Author: CuongTon
Author-email: tonkiencuong@gmail.com
License: MIT
Requires-Python: >=3.8
Requires-Dist: requests >=2.32.3
Requires-Dist: opencv-python >=4.10.0.82
Requires-Dist: pillow >=10.3.0
Requires-Dist: pdf2image >=1.17.0
Requires-Dist: numpy >=1.24.4
Requires-Dist: tqdm >=4.66.4
Requires-Dist: PyMuPDF >=1.24.5
Requires-Dist: camelot-py >=0.11.0
Requires-Dist: ghostscript >=0.7
